osgb23dtiles/__init__.py
osgb23dtiles/osgb23dtiles.py
osgb23dtiles/libs/libthreedtiles_lib_x86_64.dylib
osgb23dtiles-0.1.0.dist-info/METADATA
osgb23dtiles-0.1.0.dist-info/WHEEL
osgb23dtiles-0.1.0.dist-info/top_level.txt
osgb23dtiles-0.1.0.dist-info/RECORD
